pyastronautics/__int__.py
pyastronautics/astrodynamics/__init__.py
pyastronautics/astrodynamics/base_model.py
pyastronautics/astrodynamics/three_body_problem.py
pyastronautics/astrodynamics/two_body_problem.py
pyastronautics-0.0.40.dist-info/licenses/LICENSE
pyastronautics-0.0.40.dist-info/METADATA
pyastronautics-0.0.40.dist-info/WHEEL
pyastronautics-0.0.40.dist-info/top_level.txt
pyastronautics-0.0.40.dist-info/RECORD
