Metadata-Version: 2.4
Name: pyastronautics
Version: 0.0.40
Summary: A Python package designed for astronautical engineers, providing tools for spacecraft design analysis, simulations, and optimization
Author-email: Eduardo Ocampo <ocampoe@usc.edu>
License: 
Project-URL: Documentation, https://eduardo-ocampo.github.io/PyAstronautics/
Project-URL: Source, https://github.com/eduardo-ocampo/PyAstronautics
Classifier: Programming Language :: Python :: 3
Classifier: Operating System :: OS Independent
Requires-Python: >=3.9
License-File: LICENSE
Requires-Dist: numpy
Requires-Dist: scipy
Provides-Extra: docs
Requires-Dist: sphinx; extra == "docs"
Requires-Dist: sphinx-wagtail-theme; extra == "docs"
Requires-Dist: myst-parser; extra == "docs"
Provides-Extra: test
Requires-Dist: pytest; extra == "test"
Dynamic: license-file
